trainerbase_injector/__init__.py
trainerbase_injector/__main__.py
trainerbase_injector/api.py
trainerbase_injector/injector.cp314-win_amd64.pyd
trainerbase_injector/injector.pyi
trainerbase_injector-1.0.1.dist-info/licenses/LICENSE
trainerbase_injector-1.0.1.dist-info/METADATA
trainerbase_injector-1.0.1.dist-info/WHEEL
trainerbase_injector-1.0.1.dist-info/entry_points.txt
trainerbase_injector-1.0.1.dist-info/top_level.txt
trainerbase_injector-1.0.1.dist-info/RECORD
