Metadata-Version: 2.4
Name: trainerbase-injector
Version: 1.0.1
Summary: A tool/library allowing dynamic library injection into running processes (fork)
Home-page: https://gitlab.com/python-trainers/trainerbase-injector
Author: v01d
Author-email: v01d@v01d.ru
Keywords: injection dll so library
Classifier: Intended Audience :: Developers
Classifier: License :: OSI Approved :: MIT License
Classifier: Programming Language :: Python :: 3
Classifier: Programming Language :: Python :: 3 :: Only
Classifier: Programming Language :: Python :: 3.14
Classifier: Topic :: Software Development :: Libraries :: Python Modules
Requires-Python: >=3.14
License-File: LICENSE
Dynamic: license-file
